{
  "id": "squeeze-entry",
  "spawns": [
    { "atMs": 0, "enemyId": "sine_silent", "x": -0.3, "y": -0.08, "overrides": { "hp": 1 } },
    { "atMs": 500, "enemyId": "sine_silent", "x": 0.3, "y": -0.08, "overrides": { "hp": 1 } },
    { "atMs": 1000, "enemyId": "sine_silent", "x": -0.1, "y": -0.08, "overrides": { "hp": 1 } },
    { "atMs": 1500, "enemyId": "sine_silent", "x": 0.1, "y": -0.08, "overrides": { "hp": 1 } },
    {
      "atMs": 2200,
      "enemyId": "sine",
      "x": 0,
      "y": -0.08,
      "overrides": {
        "hp": 1,
        "fire": {
          "loop": false,
          "steps": [
            { "kind": "cooldown", "durationMs": 950 },
            {
              "kind": "burst",
              "aim": { "kind": "fixed", "angleDeg": 90 },
              "bulletId": "orb",
              "count": 1,
              "intervalMs": 1,
              "speed": 180
            }
          ]
        }
      }
    },

    { "atMs": 3600, "enemyId": "swooper", "x": -0.3, "y": -0.16, "overrides": { "hp": 2, "fire": { "steps": [] } } },
    {
      "atMs": 4300,
      "enemyId": "swooper",
      "x": 0.3,
      "y": -0.16,
      "overrides": {
        "hp": 2,
        "fire": {
          "loop": false,
          "steps": [
            { "kind": "cooldown", "durationMs": 1050 },
            {
              "kind": "burst",
              "aim": { "kind": "atPlayer" },
              "bulletId": "orb",
              "count": 1,
              "intervalMs": 1,
              "speed": 190
            }
          ]
        }
      }
    },

    {
      "atMs": 5600,
      "enemyId": "crossfire",
      "x": -0.2,
      "y": -0.12,
      "overrides": {
        "hp": 2,
        "fire": {
          "loop": false,
          "steps": [
            { "kind": "cooldown", "durationMs": 900 },
            {
              "kind": "burst",
              "aim": { "kind": "fixed", "angleDeg": 85 },
              "bulletId": "orb",
              "count": 1,
              "intervalMs": 1,
              "speed": 195
            }
          ]
        }
      }
    },
    {
      "atMs": 6400,
      "enemyId": "crossfire",
      "x": 0.2,
      "y": -0.12,
      "overrides": {
        "hp": 2,
        "fire": {
          "loop": false,
          "steps": [
            { "kind": "cooldown", "durationMs": 900 },
            {
              "kind": "burst",
              "aim": { "kind": "fixed", "angleDeg": 95 },
              "bulletId": "orb",
              "count": 1,
              "intervalMs": 1,
              "speed": 195
            }
          ]
        }
      }
    },

    { "atMs": 7800, "enemyId": "circler", "x": 0, "y": 0, "overrides": { "hp": 1 } },
    { "atMs": 8050, "enemyId": "circler", "x": 0, "y": 0, "overrides": { "hp": 1 } },
    { "atMs": 8300, "enemyId": "circler", "x": 0, "y": 0, "overrides": { "hp": 1 } },
    { "atMs": 8550, "enemyId": "circler", "x": 0, "y": 0, "overrides": { "hp": 1 } },

    {
      "atMs": 10200,
      "enemyId": "sidesweeper",
      "x": -0.42,
      "y": 1.08,
      "overrides": {
        "hp": 2,
        "fire": { "steps": [] },
        "move": {
          "steps": [
            {
              "kind": "dashTo",
              "ease": "out",
              "durationMs": 900,
              "to": { "x": 0.18, "y": -0.42 }
            },
            {
              "kind": "bezier",
              "ease": "inOut",
              "durationMs": 1800,
              "points": [
                { "x": 0, "y": 0 },
                { "x": 0.2, "y": -0.2 },
                { "x": 0.28, "y": -0.04 },
                { "x": 0.34, "y": 0.5 }
              ]
            }
          ]
        }
      }
    },
    {
      "atMs": 10850,
      "enemyId": "sidesweeper",
      "x": 0.42,
      "y": 1.08,
      "overrides": {
        "hp": 2,
        "fire": { "steps": [] },
        "move": {
          "steps": [
            {
              "kind": "dashTo",
              "ease": "out",
              "durationMs": 900,
              "to": { "x": -0.18, "y": -0.42 }
            },
            {
              "kind": "bezier",
              "ease": "inOut",
              "durationMs": 1800,
              "points": [
                { "x": 0, "y": 0 },
                { "x": -0.2, "y": -0.2 },
                { "x": -0.28, "y": -0.04 },
                { "x": -0.34, "y": 0.5 }
              ]
            }
          ]
        }
      }
    },

    {
      "atMs": 12800,
      "enemyId": "sniper",
      "x": 0,
      "y": -0.1,
      "overrides": {
        "hp": 2,
        "fire": {
          "loop": false,
          "steps": [
            { "kind": "cooldown", "durationMs": 1050 },
            {
              "kind": "burst",
              "aim": { "kind": "atPlayer" },
              "bulletId": "orb",
              "count": 1,
              "intervalMs": 1,
              "speed": 220
            }
          ]
        }
      }
    },
    {
      "atMs": 14400,
      "enemyId": "spinner",
      "x": 0,
      "y": -0.12,
      "overrides": {
        "hp": 2,
        "fire": {
          "loop": false,
          "steps": [
            { "kind": "cooldown", "durationMs": 900 },
            {
              "kind": "spray",
              "durationMs": 900,
              "ratePerSec": 3,
              "aim": { "kind": "fixed", "angleDeg": 90 },
              "bulletId": "orb",
              "speed": 190
            }
          ]
        }
      }
    },

    { "atMs": 16600, "enemyId": "sine_silent", "x": -0.28, "y": -0.08, "overrides": { "hp": 1 } },
    { "atMs": 17100, "enemyId": "sine_silent", "x": 0.28, "y": -0.08, "overrides": { "hp": 1 } },
    {
      "atMs": 17600,
      "enemyId": "sine",
      "x": 0,
      "y": -0.08,
      "overrides": { "hp": 1, "fire": { "steps": [] } }
    },

    { "atMs": 19200, "enemyId": "swooper", "x": -0.26, "y": -0.16, "overrides": { "hp": 2, "fire": { "steps": [] } } },
    { "atMs": 19800, "enemyId": "swooper", "x": 0.26, "y": -0.16, "overrides": { "hp": 2, "fire": { "steps": [] } } },
    {
      "atMs": 21000,
      "enemyId": "crossfire",
      "x": 0,
      "y": -0.12,
      "overrides": { "hp": 2, "fire": { "steps": [] } }
    }
  ]
}
